flask_simple_captcha/__init__.py
flask_simple_captcha/arial.ttf
flask_simple_captcha/config.py
flask_simple_captcha-1.1.1.dist-info/LICENSE.txt
flask_simple_captcha-1.1.1.dist-info/METADATA
flask_simple_captcha-1.1.1.dist-info/WHEEL
flask_simple_captcha-1.1.1.dist-info/top_level.txt
flask_simple_captcha-1.1.1.dist-info/RECORD
