Metadata-Version: 2.1
Name: flask-simple-captcha
Version: 1.1.1
Summary: Extremely simple, "Good Enough" captcha implemention for flask forms. No server side sessions required.
Home-page: https://github.com/cc-d/flask-simple-captcha
Author: Cary Carter
Author-email: ccarterdev@gmail.com
License: MIT
Platform: UNKNOWN
Classifier: License :: OSI Approved :: MIT License
Classifier: Programming Language :: Python :: 3
Classifier: Programming Language :: Python :: 3.7
License-File: LICENSE.txt
Requires-Dist: Werkzeug (>=0.16.0)
Requires-Dist: Pillow (>=6.1.0)
